{"games":[{"id":138,"created_at":"2024-05-01T11:31:34.000000Z","updated_at":"2024-05-01T11:31:34.000000Z","appid":1205550,"name":"New World PTR"},{"id":1,"created_at":"2024-05-01T11:31:34.000000Z","updated_at":"2024-05-01T11:31:34.000000Z","appid":4000,"name":"Garry's Mod"},{"id":2,"created_at":"2024-05-01T11:31:34.000000Z","updated_at":"2024-05-01T11:31:34.000000Z","appid":400,"name":"Portal"},{"id":3,"created_at":"2024-05-01T11:31:35.000000Z","updated_at":"2024-05-01T11:31:35.000000Z","appid":8190,"name":"Just Cause 2"},{"id":4,"created_at":"2024-05-01T11:31:35.000000Z","updated_at":"2024-05-01T11:31:35.000000Z","appid":620,"name":"Portal 2"},{"id":5,"created_at":"2024-05-01T11:31:35.000000Z","updated_at":"2024-05-01T11:31:35.000000Z","appid":105600,"name":"Terraria"},{"id":6,"created_at":"2024-05-01T11:31:35.000000Z","updated_at":"2024-05-01T11:31:35.000000Z","appid":214340,"name":"Deponia"},{"id":7,"created_at":"2024-05-01T11:31:36.000000Z","updated_at":"2024-05-01T11:31:36.000000Z","appid":49520,"name":"Borderlands 2"},{"id":8,"created_at":"2024-05-01T11:31:36.000000Z","updated_at":"2024-05-01T11:31:36.000000Z","appid":221260,"name":"Little Inferno"},{"id":9,"created_at":"2024-05-01T11:31:36.000000Z","updated_at":"2024-05-01T11:31:36.000000Z","appid":227300,"name":"Euro Truck Simulator 2"},{"id":10,"created_at":"2024-05-01T11:31:36.000000Z","updated_at":"2024-05-01T11:31:36.000000Z","appid":239030,"name":"Papers, Please"},{"id":11,"created_at":"2024-05-01T11:31:37.000000Z","updated_at":"2024-05-01T11:31:37.000000Z","appid":213670,"name":"South Park™: The Stick of Truth™"},{"id":12,"created_at":"2024-05-01T11:31:37.000000Z","updated_at":"2024-05-01T11:31:37.000000Z","appid":211820,"name":"Starbound"},{"id":13,"created_at":"2024-05-01T11:31:37.000000Z","updated_at":"2024-05-01T11:31:37.000000Z","appid":367540,"name":"Starbound - Unstable"},{"id":14,"created_at":"2024-05-01T11:31:37.000000Z","updated_at":"2024-05-01T11:31:37.000000Z","appid":224480,"name":"Octodad: Dadliest Catch"},{"id":15,"created_at":"2024-05-01T11:31:38.000000Z","updated_at":"2024-05-01T11:31:38.000000Z","appid":285070,"name":"Between Me and The Night"},{"id":16,"created_at":"2024-05-01T11:31:38.000000Z","updated_at":"2024-05-01T11:31:38.000000Z","appid":306020,"name":"Bloons TD5"},{"id":17,"created_at":"2024-05-01T11:31:38.000000Z","updated_at":"2024-05-01T11:31:38.000000Z","appid":261640,"name":"Borderlands: The Pre-Sequel"},{"id":18,"created_at":"2024-05-01T11:31:39.000000Z","updated_at":"2024-05-01T11:31:39.000000Z","appid":730,"name":"Counter-Strike 2"},{"id":19,"created_at":"2024-05-01T11:31:39.000000Z","updated_at":"2024-05-01T11:31:39.000000Z","appid":250900,"name":"The Binding of Isaac: Rebirth"},{"id":20,"created_at":"2024-05-01T11:31:39.000000Z","updated_at":"2024-05-01T11:31:39.000000Z","appid":341000,"name":"Mad Games Tycoon"},{"id":21,"created_at":"2024-05-01T11:31:40.000000Z","updated_at":"2024-05-01T11:31:40.000000Z","appid":346900,"name":"AdVenture Capitalist"},{"id":22,"created_at":"2024-05-01T11:31:40.000000Z","updated_at":"2024-05-01T11:31:40.000000Z","appid":298630,"name":"The Escapists"},{"id":23,"created_at":"2024-05-01T11:31:41.000000Z","updated_at":"2024-05-01T11:31:41.000000Z","appid":255710,"name":"Cities: Skylines"},{"id":24,"created_at":"2024-05-01T11:31:41.000000Z","updated_at":"2024-05-01T11:31:41.000000Z","appid":338530,"name":"Trouble In The Manor"},{"id":25,"created_at":"2024-05-01T11:31:41.000000Z","updated_at":"2024-05-01T11:31:41.000000Z","appid":359050,"name":"Shower With Your Dad Simulator 2015: Do You Still Shower With Your Dad"},{"id":26,"created_at":"2024-05-01T11:31:41.000000Z","updated_at":"2024-05-01T11:31:41.000000Z","appid":360830,"name":"Yooka-Laylee"},{"id":27,"created_at":"2024-05-01T11:31:41.000000Z","updated_at":"2024-05-01T11:31:41.000000Z","appid":361280,"name":"Turmoil"},{"id":28,"created_at":"2024-05-01T11:31:42.000000Z","updated_at":"2024-05-01T11:31:42.000000Z","appid":361420,"name":"ASTRONEER"},{"id":29,"created_at":"2024-05-01T11:31:42.000000Z","updated_at":"2024-05-01T11:31:42.000000Z","appid":363950,"name":"Windscape"},{"id":30,"created_at":"2024-05-01T11:31:42.000000Z","updated_at":"2024-05-01T11:31:42.000000Z","appid":363970,"name":"Clicker Heroes"},{"id":31,"created_at":"2024-05-01T11:31:42.000000Z","updated_at":"2024-05-01T11:31:42.000000Z","appid":366090,"name":"Colony Survival"},{"id":32,"created_at":"2024-05-01T11:31:43.000000Z","updated_at":"2024-05-01T11:31:43.000000Z","appid":367450,"name":"Poly Bridge"},{"id":33,"created_at":"2024-05-01T11:31:43.000000Z","updated_at":"2024-05-01T11:31:43.000000Z","appid":374320,"name":"DARK SOULS™ III"},{"id":34,"created_at":"2024-05-01T11:31:44.000000Z","updated_at":"2024-05-01T11:31:44.000000Z","appid":381120,"name":"Shoppe Keep"},{"id":35,"created_at":"2024-05-01T11:31:44.000000Z","updated_at":"2024-05-01T11:31:44.000000Z","appid":390520,"name":"PewDiePie: Legend of the Brofist"},{"id":36,"created_at":"2024-05-01T11:31:45.000000Z","updated_at":"2024-05-01T11:31:45.000000Z","appid":405640,"name":"Pony Island"},{"id":37,"created_at":"2024-05-01T11:31:45.000000Z","updated_at":"2024-05-01T11:31:45.000000Z","appid":405710,"name":"Staxel"},{"id":38,"created_at":"2024-05-01T11:31:45.000000Z","updated_at":"2024-05-01T11:31:45.000000Z","appid":406150,"name":"Refunct"},{"id":39,"created_at":"2024-05-01T11:31:46.000000Z","updated_at":"2024-05-01T11:31:46.000000Z","appid":413150,"name":"Stardew Valley"},{"id":40,"created_at":"2024-05-01T11:31:46.000000Z","updated_at":"2024-05-01T11:31:46.000000Z","appid":413410,"name":"Danganronpa: Trigger Happy Havoc"},{"id":41,"created_at":"2024-05-01T11:31:46.000000Z","updated_at":"2024-05-01T11:31:46.000000Z","appid":413420,"name":"Danganronpa 2: Goodbye Despair"},{"id":42,"created_at":"2024-05-01T11:31:46.000000Z","updated_at":"2024-05-01T11:31:46.000000Z","appid":225540,"name":"Just Cause 3"},{"id":43,"created_at":"2024-05-01T11:31:47.000000Z","updated_at":"2024-05-01T11:31:47.000000Z","appid":421040,"name":"Plantera"},{"id":44,"created_at":"2024-05-01T11:31:47.000000Z","updated_at":"2024-05-01T11:31:47.000000Z","appid":270880,"name":"American Truck Simulator"},{"id":45,"created_at":"2024-05-01T11:31:47.000000Z","updated_at":"2024-05-01T11:31:47.000000Z","appid":427520,"name":"Factorio"},{"id":46,"created_at":"2024-05-01T11:31:47.000000Z","updated_at":"2024-05-01T11:31:47.000000Z","appid":431960,"name":"Wallpaper Engine"},{"id":47,"created_at":"2024-05-01T11:31:48.000000Z","updated_at":"2024-05-01T11:31:48.000000Z","appid":433340,"name":"Slime Rancher"},{"id":48,"created_at":"2024-05-01T11:31:48.000000Z","updated_at":"2024-05-01T11:31:48.000000Z","appid":452060,"name":"Caveblazers"},{"id":49,"created_at":"2024-05-01T11:31:48.000000Z","updated_at":"2024-05-01T11:31:48.000000Z","appid":477160,"name":"Human Fall Flat"},{"id":50,"created_at":"2024-05-01T11:31:49.000000Z","updated_at":"2024-05-01T11:31:49.000000Z","appid":489830,"name":"The Elder Scrolls V: Skyrim Special Edition"},{"id":51,"created_at":"2024-05-01T11:31:49.000000Z","updated_at":"2024-05-01T11:31:49.000000Z","appid":497700,"name":"Safety First!"},{"id":52,"created_at":"2024-05-01T11:31:50.000000Z","updated_at":"2024-05-01T11:31:50.000000Z","appid":517630,"name":"Just Cause 4"},{"id":53,"created_at":"2024-05-01T11:31:50.000000Z","updated_at":"2024-05-01T11:31:50.000000Z","appid":397950,"name":"Clustertruck"},{"id":54,"created_at":"2024-05-01T11:31:50.000000Z","updated_at":"2024-05-01T11:31:50.000000Z","appid":115800,"name":"Owlboy"},{"id":55,"created_at":"2024-05-01T11:31:51.000000Z","updated_at":"2024-05-01T11:31:51.000000Z","appid":447020,"name":"Farming Simulator 17"},{"id":56,"created_at":"2024-05-01T11:31:51.000000Z","updated_at":"2024-05-01T11:31:51.000000Z","appid":555150,"name":"The First Tree"},{"id":57,"created_at":"2024-05-01T11:31:51.000000Z","updated_at":"2024-05-01T11:31:51.000000Z","appid":572890,"name":"Pikuniku"},{"id":58,"created_at":"2024-05-01T11:31:51.000000Z","updated_at":"2024-05-01T11:31:51.000000Z","appid":573110,"name":"AWAY: Journey to the Unexpected"},{"id":59,"created_at":"2024-05-01T11:31:51.000000Z","updated_at":"2024-05-01T11:31:51.000000Z","appid":574560,"name":"Dude, Stop"},{"id":60,"created_at":"2024-05-01T11:31:52.000000Z","updated_at":"2024-05-01T11:31:52.000000Z","appid":578080,"name":"PUBG: BATTLEGROUNDS"},{"id":61,"created_at":"2024-05-01T11:31:52.000000Z","updated_at":"2024-05-01T11:31:52.000000Z","appid":578330,"name":"LEGO® City Undercover"},{"id":62,"created_at":"2024-05-01T11:31:52.000000Z","updated_at":"2024-05-01T11:31:52.000000Z","appid":589590,"name":"Kindergarten"},{"id":63,"created_at":"2024-05-01T11:31:52.000000Z","updated_at":"2024-05-01T11:31:52.000000Z","appid":593280,"name":"Cat Quest"},{"id":64,"created_at":"2024-05-01T11:31:53.000000Z","updated_at":"2024-05-01T11:31:53.000000Z","appid":593600,"name":"PixARK"},{"id":65,"created_at":"2024-05-01T11:31:53.000000Z","updated_at":"2024-05-01T11:31:53.000000Z","appid":610080,"name":"Realm Grinder"},{"id":66,"created_at":"2024-05-01T11:31:53.000000Z","updated_at":"2024-05-01T11:31:53.000000Z","appid":616520,"name":"Cheap Golf"},{"id":67,"created_at":"2024-05-01T11:31:53.000000Z","updated_at":"2024-05-01T11:31:53.000000Z","appid":652980,"name":"Loading Screen Simulator"},{"id":68,"created_at":"2024-05-01T11:31:54.000000Z","updated_at":"2024-05-01T11:31:54.000000Z","appid":668210,"name":"Super Fancy Pants Adventure"},{"id":69,"created_at":"2024-05-01T11:31:54.000000Z","updated_at":"2024-05-01T11:31:54.000000Z","appid":674940,"name":"Stick Fight: The Game"},{"id":70,"created_at":"2024-05-01T11:31:54.000000Z","updated_at":"2024-05-01T11:31:54.000000Z","appid":240720,"name":"Getting Over It with Bennett Foddy"},{"id":71,"created_at":"2024-05-01T11:31:54.000000Z","updated_at":"2024-05-01T11:31:54.000000Z","appid":699920,"name":"Despotism 3k"},{"id":72,"created_at":"2024-05-01T11:31:55.000000Z","updated_at":"2024-05-01T11:31:55.000000Z","appid":702670,"name":"Donut County"},{"id":73,"created_at":"2024-05-01T11:31:55.000000Z","updated_at":"2024-05-01T11:31:55.000000Z","appid":703840,"name":"Animal Super Squad"},{"id":74,"created_at":"2024-05-01T11:31:55.000000Z","updated_at":"2024-05-01T11:31:55.000000Z","appid":711660,"name":"CHUCHEL"},{"id":75,"created_at":"2024-05-01T11:31:55.000000Z","updated_at":"2024-05-01T11:31:55.000000Z","appid":567640,"name":"Danganronpa V3: Killing Harmony"},{"id":76,"created_at":"2024-05-01T11:31:56.000000Z","updated_at":"2024-05-01T11:31:56.000000Z","appid":751780,"name":"Forager"},{"id":77,"created_at":"2024-05-01T11:31:56.000000Z","updated_at":"2024-05-01T11:31:56.000000Z","appid":496300,"name":"Kingdom: New Lands"},{"id":78,"created_at":"2024-05-01T11:31:57.000000Z","updated_at":"2024-05-01T11:31:57.000000Z","appid":795040,"name":"E.Z"},{"id":79,"created_at":"2024-05-01T11:31:57.000000Z","updated_at":"2024-05-01T11:31:57.000000Z","appid":799070,"name":"Zup! 8"},{"id":80,"created_at":"2024-05-01T11:31:57.000000Z","updated_at":"2024-05-01T11:31:57.000000Z","appid":252490,"name":"Rust"},{"id":81,"created_at":"2024-05-01T11:31:58.000000Z","updated_at":"2024-05-01T11:31:58.000000Z","appid":700580,"name":"Rust - Staging Branch"},{"id":82,"created_at":"2024-05-01T11:31:58.000000Z","updated_at":"2024-05-01T11:31:58.000000Z","appid":810040,"name":"Swords 'n Magic and Stuff"},{"id":83,"created_at":"2024-05-01T11:31:58.000000Z","updated_at":"2024-05-01T11:31:58.000000Z","appid":814370,"name":"Monster Sanctuary"},{"id":84,"created_at":"2024-05-01T11:31:58.000000Z","updated_at":"2024-05-01T11:31:58.000000Z","appid":837470,"name":"Untitled Goose Game"},{"id":85,"created_at":"2024-05-01T11:31:59.000000Z","updated_at":"2024-05-01T11:31:59.000000Z","appid":860890,"name":"Factory Town"},{"id":86,"created_at":"2024-05-01T11:31:59.000000Z","updated_at":"2024-05-01T11:31:59.000000Z","appid":880940,"name":"Pummel Party"},{"id":87,"created_at":"2024-05-01T11:32:00.000000Z","updated_at":"2024-05-01T11:32:00.000000Z","appid":894940,"name":"Littlewood"},{"id":88,"created_at":"2024-05-01T11:32:00.000000Z","updated_at":"2024-05-01T11:32:00.000000Z","appid":897330,"name":"Coloring Pixels"},{"id":89,"created_at":"2024-05-01T11:32:00.000000Z","updated_at":"2024-05-01T11:32:00.000000Z","appid":900270,"name":"Reventure"},{"id":90,"created_at":"2024-05-01T11:32:00.000000Z","updated_at":"2024-05-01T11:32:00.000000Z","appid":914710,"name":"Cat Quest II"},{"id":91,"created_at":"2024-05-01T11:32:01.000000Z","updated_at":"2024-05-01T11:32:01.000000Z","appid":915460,"name":"ULTIMATE HARDBASS DEFENCE"},{"id":92,"created_at":"2024-05-01T11:32:01.000000Z","updated_at":"2024-05-01T11:32:01.000000Z","appid":925950,"name":"Here Comes Niko!"},{"id":93,"created_at":"2024-05-01T11:32:01.000000Z","updated_at":"2024-05-01T11:32:01.000000Z","appid":792100,"name":"7 Billion Humans"},{"id":94,"created_at":"2024-05-01T11:32:01.000000Z","updated_at":"2024-05-01T11:32:01.000000Z","appid":945360,"name":"Among Us"},{"id":95,"created_at":"2024-05-01T11:32:02.000000Z","updated_at":"2024-05-01T11:32:02.000000Z","appid":953880,"name":"First Class Trouble"},{"id":96,"created_at":"2024-05-01T11:32:02.000000Z","updated_at":"2024-05-01T11:32:02.000000Z","appid":963710,"name":"Lost in Vivo"},{"id":97,"created_at":"2024-05-01T11:32:02.000000Z","updated_at":"2024-05-01T11:32:02.000000Z","appid":969990,"name":"SpongeBob SquarePants: Battle for Bikini Bottom - Rehydrated"},{"id":98,"created_at":"2024-05-01T11:32:03.000000Z","updated_at":"2024-05-01T11:32:03.000000Z","appid":996580,"name":"Spyro™ Reignited Trilogy"},{"id":99,"created_at":"2024-05-01T11:32:03.000000Z","updated_at":"2024-05-01T11:32:03.000000Z","appid":519860,"name":"DUSK"},{"id":100,"created_at":"2024-05-01T11:32:03.000000Z","updated_at":"2024-05-01T11:32:03.000000Z","appid":1051200,"name":"Trover Saves the Universe"},{"id":101,"created_at":"2024-05-01T11:32:03.000000Z","updated_at":"2024-05-01T11:32:03.000000Z","appid":1055540,"name":"A Short Hike"},{"id":102,"created_at":"2024-05-01T11:32:04.000000Z","updated_at":"2024-05-01T11:32:04.000000Z","appid":1069740,"name":"Seen"},{"id":103,"created_at":"2024-05-01T11:32:04.000000Z","updated_at":"2024-05-01T11:32:04.000000Z","appid":1089980,"name":"The Henry Stickmin Collection"},{"id":104,"created_at":"2024-05-01T11:32:05.000000Z","updated_at":"2024-05-01T11:32:05.000000Z","appid":1149460,"name":"Icarus"},{"id":105,"created_at":"2024-05-01T11:32:05.000000Z","updated_at":"2024-05-01T11:32:05.000000Z","appid":1157340,"name":"Hentai Killer"},{"id":106,"created_at":"2024-05-01T11:32:05.000000Z","updated_at":"2024-05-01T11:32:05.000000Z","appid":1162280,"name":"Eternal Hope"},{"id":107,"created_at":"2024-05-01T11:32:05.000000Z","updated_at":"2024-05-01T11:32:05.000000Z","appid":1201550,"name":"Mad Experiments: Escape Room"},{"id":108,"created_at":"2024-05-01T11:32:06.000000Z","updated_at":"2024-05-01T11:32:06.000000Z","appid":1205450,"name":"Turnip Boy Commits Tax Evasion"},{"id":109,"created_at":"2024-05-01T11:32:06.000000Z","updated_at":"2024-05-01T11:32:06.000000Z","appid":1063730,"name":"New World"},{"id":110,"created_at":"2024-05-01T11:32:06.000000Z","updated_at":"2024-05-01T11:32:06.000000Z","appid":1251460,"name":"Tanuki Sunset"},{"id":111,"created_at":"2024-05-01T11:32:06.000000Z","updated_at":"2024-05-01T11:32:06.000000Z","appid":397540,"name":"Borderlands 3"},{"id":112,"created_at":"2024-05-01T11:32:07.000000Z","updated_at":"2024-05-01T11:32:07.000000Z","appid":1263820,"name":"Sokpop S07: sok-worlds"},{"id":113,"created_at":"2024-05-01T11:32:07.000000Z","updated_at":"2024-05-01T11:32:07.000000Z","appid":1269950,"name":"Buddy Simulator 1984"},{"id":114,"created_at":"2024-05-01T11:32:07.000000Z","updated_at":"2024-05-01T11:32:07.000000Z","appid":1333910,"name":"Sizeable"},{"id":115,"created_at":"2024-05-01T11:32:07.000000Z","updated_at":"2024-05-01T11:32:07.000000Z","appid":1338130,"name":"Sokpop S08: Popo's Tower"},{"id":116,"created_at":"2024-05-01T11:32:08.000000Z","updated_at":"2024-05-01T11:32:08.000000Z","appid":1356280,"name":"Kitaria Fables"},{"id":117,"created_at":"2024-05-01T11:32:08.000000Z","updated_at":"2024-05-01T11:32:08.000000Z","appid":1454400,"name":"Cookie Clicker"},{"id":118,"created_at":"2024-05-01T11:32:09.000000Z","updated_at":"2024-05-01T11:32:09.000000Z","appid":1207400,"name":"Sokpop S06: Klym"},{"id":119,"created_at":"2024-05-01T11:32:09.000000Z","updated_at":"2024-05-01T11:32:09.000000Z","appid":1211540,"name":"Sokpop S06: bobo robot"},{"id":120,"created_at":"2024-05-01T11:32:09.000000Z","updated_at":"2024-05-01T11:32:09.000000Z","appid":1212100,"name":"Sokpop S06: fishy"},{"id":121,"created_at":"2024-05-01T11:32:09.000000Z","updated_at":"2024-05-01T11:32:09.000000Z","appid":1215410,"name":"Sokpop S06: Sproots"},{"id":122,"created_at":"2024-05-01T11:32:10.000000Z","updated_at":"2024-05-01T11:32:10.000000Z","appid":1218790,"name":"Sokpop S06: Good Goods Incorporated"},{"id":123,"created_at":"2024-05-01T11:32:10.000000Z","updated_at":"2024-05-01T11:32:10.000000Z","appid":1218890,"name":"Sokpop S06: Ollie & Bollie: Outdoor Estate"},{"id":124,"created_at":"2024-05-01T11:32:10.000000Z","updated_at":"2024-05-01T11:32:10.000000Z","appid":1218920,"name":"Sokpop S06: Sunset Kingdom"},{"id":125,"created_at":"2024-05-01T11:32:10.000000Z","updated_at":"2024-05-01T11:32:10.000000Z","appid":1468260,"name":"Leaf Blower Revolution - Idle Game"},{"id":126,"created_at":"2024-05-01T11:32:11.000000Z","updated_at":"2024-05-01T11:32:11.000000Z","appid":1501610,"name":"Nova Lands"},{"id":127,"created_at":"2024-05-01T11:32:11.000000Z","updated_at":"2024-05-01T11:32:11.000000Z","appid":1510620,"name":"Sokpop S10: Pocket Watch"},{"id":128,"created_at":"2024-05-01T11:32:11.000000Z","updated_at":"2024-05-01T11:32:11.000000Z","appid":1552310,"name":"JANITOR BLEEDS"},{"id":129,"created_at":"2024-05-01T11:32:11.000000Z","updated_at":"2024-05-01T11:32:11.000000Z","appid":1603410,"name":"Lost Nova"},{"id":130,"created_at":"2024-05-01T11:32:12.000000Z","updated_at":"2024-05-01T11:32:12.000000Z","appid":1621690,"name":"Core Keeper"},{"id":131,"created_at":"2024-05-01T11:32:12.000000Z","updated_at":"2024-05-01T11:32:12.000000Z","appid":1656780,"name":"Hero's Hour"},{"id":132,"created_at":"2024-05-01T11:32:12.000000Z","updated_at":"2024-05-01T11:32:12.000000Z","appid":1671340,"name":"Fears to Fathom - Episode 1"},{"id":133,"created_at":"2024-05-01T11:32:12.000000Z","updated_at":"2024-05-01T11:32:12.000000Z","appid":1695480,"name":"Hellblusser"},{"id":134,"created_at":"2024-05-01T11:32:12.000000Z","updated_at":"2024-05-01T11:32:12.000000Z","appid":1785150,"name":"Friends vs Friends"},{"id":135,"created_at":"2024-05-01T11:32:13.000000Z","updated_at":"2024-05-01T11:32:13.000000Z","appid":1846170,"name":"Iron Lung"},{"id":136,"created_at":"2024-05-01T11:32:13.000000Z","updated_at":"2024-05-01T11:32:13.000000Z","appid":1942280,"name":"Brotato"},{"id":137,"created_at":"2024-05-01T11:32:13.000000Z","updated_at":"2024-05-01T11:32:13.000000Z","appid":440,"name":"Team Fortress 2"}],"users":[{"id":2,"name":"Joy","steam_user_id":76561198350892110,"created_at":"2024-05-01T11:31:29.000000Z","updated_at":"2024-05-01T11:31:29.000000Z","game_stats":[{"id":137,"created_at":"2024-05-01T11:32:14.000000Z","updated_at":"2024-05-01T11:32:14.000000Z","user_id":2,"game_id":138,"total":133,"achieved":52},{"id":138,"created_at":"2024-05-01T11:32:14.000000Z","updated_at":"2024-05-01T11:32:14.000000Z","user_id":2,"game_id":1,"total":29,"achieved":20},{"id":139,"created_at":"2024-05-01T11:32:14.000000Z","updated_at":"2024-05-01T11:32:14.000000Z","user_id":2,"game_id":2,"total":15,"achieved":15},{"id":140,"created_at":"2024-05-01T11:32:14.000000Z","updated_at":"2024-05-01T11:32:14.000000Z","user_id":2,"game_id":3,"total":50,"achieved":50},{"id":141,"created_at":"2024-05-01T11:32:14.000000Z","updated_at":"2024-05-01T11:32:14.000000Z","user_id":2,"game_id":4,"total":51,"achieved":51},{"id":142,"created_at":"2024-05-01T11:32:15.000000Z","updated_at":"2024-05-01T11:32:15.000000Z","user_id":2,"game_id":5,"total":115,"achieved":115},{"id":143,"created_at":"2024-05-01T11:32:15.000000Z","updated_at":"2024-05-01T11:32:15.000000Z","user_id":2,"game_id":6,"total":19,"achieved":19},{"id":144,"created_at":"2024-05-01T11:32:15.000000Z","updated_at":"2024-05-01T11:32:15.000000Z","user_id":2,"game_id":7,"total":75,"achieved":75},{"id":145,"created_at":"2024-05-01T11:32:15.000000Z","updated_at":"2024-05-01T11:32:15.000000Z","user_id":2,"game_id":8,"total":22,"achieved":22},{"id":146,"created_at":"2024-05-01T11:32:15.000000Z","updated_at":"2024-05-01T11:32:15.000000Z","user_id":2,"game_id":9,"total":87,"achieved":87},{"id":147,"created_at":"2024-05-01T11:32:15.000000Z","updated_at":"2024-05-01T11:32:15.000000Z","user_id":2,"game_id":10,"total":13,"achieved":13},{"id":148,"created_at":"2024-05-01T11:32:15.000000Z","updated_at":"2024-05-01T11:32:15.000000Z","user_id":2,"game_id":11,"total":50,"achieved":50},{"id":149,"created_at":"2024-05-01T11:32:15.000000Z","updated_at":"2024-05-01T11:32:15.000000Z","user_id":2,"game_id":12,"total":51,"achieved":51},{"id":150,"created_at":"2024-05-01T11:32:15.000000Z","updated_at":"2024-05-01T11:32:15.000000Z","user_id":2,"game_id":13,"total":51,"achieved":0},{"id":151,"created_at":"2024-05-01T11:32:15.000000Z","updated_at":"2024-05-01T11:32:15.000000Z","user_id":2,"game_id":14,"total":32,"achieved":32},{"id":152,"created_at":"2024-05-01T11:32:15.000000Z","updated_at":"2024-05-01T11:32:15.000000Z","user_id":2,"game_id":15,"total":18,"achieved":18},{"id":153,"created_at":"2024-05-01T11:32:15.000000Z","updated_at":"2024-05-01T11:32:15.000000Z","user_id":2,"game_id":16,"total":125,"achieved":125},{"id":154,"created_at":"2024-05-01T11:32:15.000000Z","updated_at":"2024-05-01T11:32:15.000000Z","user_id":2,"game_id":17,"total":63,"achieved":51},{"id":155,"created_at":"2024-05-01T11:32:15.000000Z","updated_at":"2024-05-01T11:32:15.000000Z","user_id":2,"game_id":18,"total":1,"achieved":1},{"id":156,"created_at":"2024-05-01T11:32:16.000000Z","updated_at":"2024-05-01T11:32:16.000000Z","user_id":2,"game_id":19,"total":637,"achieved":406},{"id":157,"created_at":"2024-05-01T11:32:16.000000Z","updated_at":"2024-05-01T11:32:16.000000Z","user_id":2,"game_id":20,"total":39,"achieved":39},{"id":158,"created_at":"2024-05-01T11:32:16.000000Z","updated_at":"2024-05-01T11:32:16.000000Z","user_id":2,"game_id":21,"total":31,"achieved":31},{"id":159,"created_at":"2024-05-01T11:32:16.000000Z","updated_at":"2024-05-01T11:32:16.000000Z","user_id":2,"game_id":22,"total":37,"achieved":0},{"id":160,"created_at":"2024-05-01T11:32:16.000000Z","updated_at":"2024-05-01T11:32:16.000000Z","user_id":2,"game_id":23,"total":127,"achieved":105},{"id":161,"created_at":"2024-05-01T11:32:17.000000Z","updated_at":"2024-05-01T11:32:17.000000Z","user_id":2,"game_id":24,"total":21,"achieved":17},{"id":162,"created_at":"2024-05-01T11:32:17.000000Z","updated_at":"2024-05-01T11:32:17.000000Z","user_id":2,"game_id":25,"total":21,"achieved":17},{"id":163,"created_at":"2024-05-01T11:32:17.000000Z","updated_at":"2024-05-01T11:32:17.000000Z","user_id":2,"game_id":26,"total":35,"achieved":35},{"id":164,"created_at":"2024-05-01T11:32:17.000000Z","updated_at":"2024-05-01T11:32:17.000000Z","user_id":2,"game_id":27,"total":31,"achieved":31},{"id":165,"created_at":"2024-05-01T11:32:17.000000Z","updated_at":"2024-05-01T11:32:17.000000Z","user_id":2,"game_id":28,"total":56,"achieved":56},{"id":166,"created_at":"2024-05-01T11:32:17.000000Z","updated_at":"2024-05-01T11:32:17.000000Z","user_id":2,"game_id":29,"total":12,"achieved":0},{"id":167,"created_at":"2024-05-01T11:32:17.000000Z","updated_at":"2024-05-01T11:32:17.000000Z","user_id":2,"game_id":30,"total":111,"achieved":111},{"id":168,"created_at":"2024-05-01T11:32:17.000000Z","updated_at":"2024-05-01T11:32:17.000000Z","user_id":2,"game_id":31,"total":50,"achieved":50},{"id":169,"created_at":"2024-05-01T11:32:17.000000Z","updated_at":"2024-05-01T11:32:17.000000Z","user_id":2,"game_id":32,"total":22,"achieved":22},{"id":170,"created_at":"2024-05-01T11:32:18.000000Z","updated_at":"2024-05-01T11:32:18.000000Z","user_id":2,"game_id":33,"total":43,"achieved":39},{"id":171,"created_at":"2024-05-01T11:32:18.000000Z","updated_at":"2024-05-01T11:32:18.000000Z","user_id":2,"game_id":34,"total":31,"achieved":31},{"id":172,"created_at":"2024-05-01T11:32:18.000000Z","updated_at":"2024-05-01T11:32:18.000000Z","user_id":2,"game_id":35,"total":58,"achieved":58},{"id":173,"created_at":"2024-05-01T11:32:18.000000Z","updated_at":"2024-05-01T11:32:18.000000Z","user_id":2,"game_id":36,"total":20,"achieved":20},{"id":174,"created_at":"2024-05-01T11:32:18.000000Z","updated_at":"2024-05-01T11:32:18.000000Z","user_id":2,"game_id":37,"total":28,"achieved":0},{"id":175,"created_at":"2024-05-01T11:32:18.000000Z","updated_at":"2024-05-01T11:32:18.000000Z","user_id":2,"game_id":38,"total":10,"achieved":10},{"id":176,"created_at":"2024-05-01T11:32:19.000000Z","updated_at":"2024-05-01T11:32:19.000000Z","user_id":2,"game_id":39,"total":49,"achieved":49},{"id":177,"created_at":"2024-05-01T11:32:19.000000Z","updated_at":"2024-05-01T11:32:19.000000Z","user_id":2,"game_id":40,"total":38,"achieved":0},{"id":178,"created_at":"2024-05-01T11:32:19.000000Z","updated_at":"2024-05-01T11:32:19.000000Z","user_id":2,"game_id":41,"total":47,"achieved":0},{"id":179,"created_at":"2024-05-01T11:32:19.000000Z","updated_at":"2024-05-01T11:32:19.000000Z","user_id":2,"game_id":42,"total":66,"achieved":66},{"id":180,"created_at":"2024-05-01T11:32:19.000000Z","updated_at":"2024-05-01T11:32:19.000000Z","user_id":2,"game_id":43,"total":29,"achieved":29},{"id":181,"created_at":"2024-05-01T11:32:19.000000Z","updated_at":"2024-05-01T11:32:19.000000Z","user_id":2,"game_id":44,"total":100,"achieved":96},{"id":182,"created_at":"2024-05-01T11:32:19.000000Z","updated_at":"2024-05-01T11:32:19.000000Z","user_id":2,"game_id":45,"total":38,"achieved":38},{"id":183,"created_at":"2024-05-01T11:32:19.000000Z","updated_at":"2024-05-01T11:32:19.000000Z","user_id":2,"game_id":46,"total":17,"achieved":17},{"id":184,"created_at":"2024-05-01T11:32:19.000000Z","updated_at":"2024-05-01T11:32:19.000000Z","user_id":2,"game_id":47,"total":57,"achieved":57},{"id":185,"created_at":"2024-05-01T11:32:19.000000Z","updated_at":"2024-05-01T11:32:19.000000Z","user_id":2,"game_id":48,"total":21,"achieved":11},{"id":186,"created_at":"2024-05-01T11:32:20.000000Z","updated_at":"2024-05-01T11:32:20.000000Z","user_id":2,"game_id":49,"total":123,"achieved":123},{"id":187,"created_at":"2024-05-01T11:32:20.000000Z","updated_at":"2024-05-01T11:32:20.000000Z","user_id":2,"game_id":50,"total":75,"achieved":75},{"id":188,"created_at":"2024-05-01T11:32:20.000000Z","updated_at":"2024-05-01T11:32:20.000000Z","user_id":2,"game_id":51,"total":34,"achieved":34},{"id":189,"created_at":"2024-05-01T11:32:21.000000Z","updated_at":"2024-05-01T11:32:21.000000Z","user_id":2,"game_id":52,"total":61,"achieved":61},{"id":190,"created_at":"2024-05-01T11:32:21.000000Z","updated_at":"2024-05-01T11:32:21.000000Z","user_id":2,"game_id":53,"total":19,"achieved":19},{"id":191,"created_at":"2024-05-01T11:32:21.000000Z","updated_at":"2024-05-01T11:32:21.000000Z","user_id":2,"game_id":54,"total":12,"achieved":12},{"id":192,"created_at":"2024-05-01T11:32:21.000000Z","updated_at":"2024-05-01T11:32:21.000000Z","user_id":2,"game_id":55,"total":17,"achieved":17},{"id":193,"created_at":"2024-05-01T11:32:21.000000Z","updated_at":"2024-05-01T11:32:21.000000Z","user_id":2,"game_id":56,"total":14,"achieved":14},{"id":194,"created_at":"2024-05-01T11:32:21.000000Z","updated_at":"2024-05-01T11:32:21.000000Z","user_id":2,"game_id":57,"total":14,"achieved":14},{"id":195,"created_at":"2024-05-01T11:32:21.000000Z","updated_at":"2024-05-01T11:32:21.000000Z","user_id":2,"game_id":58,"total":16,"achieved":16},{"id":196,"created_at":"2024-05-01T11:32:21.000000Z","updated_at":"2024-05-01T11:32:21.000000Z","user_id":2,"game_id":59,"total":22,"achieved":22},{"id":197,"created_at":"2024-05-01T11:32:21.000000Z","updated_at":"2024-05-01T11:32:21.000000Z","user_id":2,"game_id":60,"total":37,"achieved":15},{"id":198,"created_at":"2024-05-01T11:32:21.000000Z","updated_at":"2024-05-01T11:32:21.000000Z","user_id":2,"game_id":61,"total":48,"achieved":48},{"id":199,"created_at":"2024-05-01T11:32:21.000000Z","updated_at":"2024-05-01T11:32:21.000000Z","user_id":2,"game_id":62,"total":8,"achieved":8},{"id":200,"created_at":"2024-05-01T11:32:21.000000Z","updated_at":"2024-05-01T11:32:21.000000Z","user_id":2,"game_id":63,"total":12,"achieved":12},{"id":201,"created_at":"2024-05-01T11:32:22.000000Z","updated_at":"2024-05-01T11:32:22.000000Z","user_id":2,"game_id":64,"total":35,"achieved":35},{"id":202,"created_at":"2024-05-01T11:32:22.000000Z","updated_at":"2024-05-01T11:32:22.000000Z","user_id":2,"game_id":65,"total":14,"achieved":14},{"id":203,"created_at":"2024-05-01T11:32:22.000000Z","updated_at":"2024-05-01T11:32:22.000000Z","user_id":2,"game_id":66,"total":4,"achieved":4},{"id":204,"created_at":"2024-05-01T11:32:22.000000Z","updated_at":"2024-05-01T11:32:22.000000Z","user_id":2,"game_id":67,"total":20,"achieved":20},{"id":205,"created_at":"2024-05-01T11:32:22.000000Z","updated_at":"2024-05-01T11:32:22.000000Z","user_id":2,"game_id":68,"total":16,"achieved":0},{"id":206,"created_at":"2024-05-01T11:32:22.000000Z","updated_at":"2024-05-01T11:32:22.000000Z","user_id":2,"game_id":69,"total":28,"achieved":28},{"id":207,"created_at":"2024-05-01T11:32:22.000000Z","updated_at":"2024-05-01T11:32:22.000000Z","user_id":2,"game_id":70,"total":3,"achieved":3},{"id":208,"created_at":"2024-05-01T11:32:22.000000Z","updated_at":"2024-05-01T11:32:22.000000Z","user_id":2,"game_id":71,"total":30,"achieved":29},{"id":209,"created_at":"2024-05-01T11:32:22.000000Z","updated_at":"2024-05-01T11:32:22.000000Z","user_id":2,"game_id":72,"total":20,"achieved":20},{"id":210,"created_at":"2024-05-01T11:32:22.000000Z","updated_at":"2024-05-01T11:32:22.000000Z","user_id":2,"game_id":73,"total":17,"achieved":14},{"id":211,"created_at":"2024-05-01T11:32:23.000000Z","updated_at":"2024-05-01T11:32:23.000000Z","user_id":2,"game_id":74,"total":7,"achieved":7},{"id":212,"created_at":"2024-05-01T11:32:23.000000Z","updated_at":"2024-05-01T11:32:23.000000Z","user_id":2,"game_id":75,"total":41,"achieved":0},{"id":213,"created_at":"2024-05-01T11:32:23.000000Z","updated_at":"2024-05-01T11:32:23.000000Z","user_id":2,"game_id":76,"total":103,"achieved":103},{"id":214,"created_at":"2024-05-01T11:32:24.000000Z","updated_at":"2024-05-01T11:32:24.000000Z","user_id":2,"game_id":77,"total":34,"achieved":0},{"id":215,"created_at":"2024-05-01T11:32:24.000000Z","updated_at":"2024-05-01T11:32:24.000000Z","user_id":2,"game_id":78,"total":129,"achieved":126},{"id":216,"created_at":"2024-05-01T11:32:25.000000Z","updated_at":"2024-05-01T11:32:25.000000Z","user_id":2,"game_id":79,"total":2220,"achieved":2220},{"id":217,"created_at":"2024-05-01T11:32:25.000000Z","updated_at":"2024-05-01T11:32:25.000000Z","user_id":2,"game_id":80,"total":92,"achieved":50},{"id":218,"created_at":"2024-05-01T11:32:25.000000Z","updated_at":"2024-05-01T11:32:25.000000Z","user_id":2,"game_id":81,"total":6,"achieved":0},{"id":219,"created_at":"2024-05-01T11:32:25.000000Z","updated_at":"2024-05-01T11:32:25.000000Z","user_id":2,"game_id":82,"total":13,"achieved":0},{"id":220,"created_at":"2024-05-01T11:32:25.000000Z","updated_at":"2024-05-01T11:32:25.000000Z","user_id":2,"game_id":83,"total":41,"achieved":41},{"id":221,"created_at":"2024-05-01T11:32:25.000000Z","updated_at":"2024-05-01T11:32:25.000000Z","user_id":2,"game_id":84,"total":25,"achieved":25},{"id":222,"created_at":"2024-05-01T11:32:26.000000Z","updated_at":"2024-05-01T11:32:26.000000Z","user_id":2,"game_id":85,"total":32,"achieved":32},{"id":223,"created_at":"2024-05-01T11:32:27.000000Z","updated_at":"2024-05-01T11:32:27.000000Z","user_id":2,"game_id":86,"total":31,"achieved":0},{"id":224,"created_at":"2024-05-01T11:32:27.000000Z","updated_at":"2024-05-01T11:32:27.000000Z","user_id":2,"game_id":87,"total":60,"achieved":60},{"id":225,"created_at":"2024-05-01T11:32:27.000000Z","updated_at":"2024-05-01T11:32:27.000000Z","user_id":2,"game_id":88,"total":1653,"achieved":1653},{"id":226,"created_at":"2024-05-01T11:32:27.000000Z","updated_at":"2024-05-01T11:32:27.000000Z","user_id":2,"game_id":89,"total":101,"achieved":101},{"id":227,"created_at":"2024-05-01T11:32:27.000000Z","updated_at":"2024-05-01T11:32:27.000000Z","user_id":2,"game_id":90,"total":9,"achieved":9},{"id":228,"created_at":"2024-05-01T11:32:27.000000Z","updated_at":"2024-05-01T11:32:27.000000Z","user_id":2,"game_id":91,"total":33,"achieved":33},{"id":229,"created_at":"2024-05-01T11:32:28.000000Z","updated_at":"2024-05-01T11:32:28.000000Z","user_id":2,"game_id":92,"total":7,"achieved":7},{"id":230,"created_at":"2024-05-01T11:32:28.000000Z","updated_at":"2024-05-01T11:32:28.000000Z","user_id":2,"game_id":93,"total":19,"achieved":19},{"id":231,"created_at":"2024-05-01T11:32:28.000000Z","updated_at":"2024-05-01T11:32:28.000000Z","user_id":2,"game_id":94,"total":33,"achieved":0},{"id":232,"created_at":"2024-05-01T11:32:29.000000Z","updated_at":"2024-05-01T11:32:29.000000Z","user_id":2,"game_id":95,"total":17,"achieved":0},{"id":233,"created_at":"2024-05-01T11:32:29.000000Z","updated_at":"2024-05-01T11:32:29.000000Z","user_id":2,"game_id":96,"total":9,"achieved":0},{"id":234,"created_at":"2024-05-01T11:32:29.000000Z","updated_at":"2024-05-01T11:32:29.000000Z","user_id":2,"game_id":97,"total":32,"achieved":32},{"id":235,"created_at":"2024-05-01T11:32:29.000000Z","updated_at":"2024-05-01T11:32:29.000000Z","user_id":2,"game_id":98,"total":105,"achieved":105},{"id":236,"created_at":"2024-05-01T11:32:30.000000Z","updated_at":"2024-05-01T11:32:30.000000Z","user_id":2,"game_id":99,"total":30,"achieved":0},{"id":237,"created_at":"2024-05-01T11:32:30.000000Z","updated_at":"2024-05-01T11:32:30.000000Z","user_id":2,"game_id":100,"total":27,"achieved":27},{"id":238,"created_at":"2024-05-01T11:32:30.000000Z","updated_at":"2024-05-01T11:32:30.000000Z","user_id":2,"game_id":101,"total":12,"achieved":12},{"id":239,"created_at":"2024-05-01T11:32:31.000000Z","updated_at":"2024-05-01T11:32:31.000000Z","user_id":2,"game_id":102,"total":210,"achieved":207},{"id":240,"created_at":"2024-05-01T11:32:31.000000Z","updated_at":"2024-05-01T11:32:31.000000Z","user_id":2,"game_id":103,"total":82,"achieved":82},{"id":241,"created_at":"2024-05-01T11:32:31.000000Z","updated_at":"2024-05-01T11:32:31.000000Z","user_id":2,"game_id":104,"total":40,"achieved":0},{"id":242,"created_at":"2024-05-01T11:32:32.000000Z","updated_at":"2024-05-01T11:32:32.000000Z","user_id":2,"game_id":105,"total":7,"achieved":7},{"id":243,"created_at":"2024-05-01T11:32:32.000000Z","updated_at":"2024-05-01T11:32:32.000000Z","user_id":2,"game_id":106,"total":29,"achieved":29},{"id":244,"created_at":"2024-05-01T11:32:32.000000Z","updated_at":"2024-05-01T11:32:32.000000Z","user_id":2,"game_id":107,"total":13,"achieved":13},{"id":245,"created_at":"2024-05-01T11:32:32.000000Z","updated_at":"2024-05-01T11:32:32.000000Z","user_id":2,"game_id":108,"total":37,"achieved":37},{"id":246,"created_at":"2024-05-01T11:32:32.000000Z","updated_at":"2024-05-01T11:32:32.000000Z","user_id":2,"game_id":109,"total":133,"achieved":95},{"id":247,"created_at":"2024-05-01T11:32:33.000000Z","updated_at":"2024-05-01T11:32:33.000000Z","user_id":2,"game_id":110,"total":15,"achieved":9},{"id":248,"created_at":"2024-05-01T11:32:33.000000Z","updated_at":"2024-05-01T11:32:33.000000Z","user_id":2,"game_id":111,"total":81,"achieved":81},{"id":249,"created_at":"2024-05-01T11:32:33.000000Z","updated_at":"2024-05-01T11:32:33.000000Z","user_id":2,"game_id":112,"total":4,"achieved":4},{"id":250,"created_at":"2024-05-01T11:32:33.000000Z","updated_at":"2024-05-01T11:32:33.000000Z","user_id":2,"game_id":113,"total":30,"achieved":30},{"id":251,"created_at":"2024-05-01T11:32:34.000000Z","updated_at":"2024-05-01T11:32:34.000000Z","user_id":2,"game_id":114,"total":16,"achieved":16},{"id":252,"created_at":"2024-05-01T11:32:34.000000Z","updated_at":"2024-05-01T11:32:34.000000Z","user_id":2,"game_id":115,"total":8,"achieved":8},{"id":253,"created_at":"2024-05-01T11:32:34.000000Z","updated_at":"2024-05-01T11:32:34.000000Z","user_id":2,"game_id":116,"total":41,"achieved":41},{"id":254,"created_at":"2024-05-01T11:32:35.000000Z","updated_at":"2024-05-01T11:32:35.000000Z","user_id":2,"game_id":117,"total":637,"achieved":637},{"id":255,"created_at":"2024-05-01T11:32:35.000000Z","updated_at":"2024-05-01T11:32:35.000000Z","user_id":2,"game_id":118,"total":4,"achieved":4},{"id":256,"created_at":"2024-05-01T11:32:35.000000Z","updated_at":"2024-05-01T11:32:35.000000Z","user_id":2,"game_id":119,"total":8,"achieved":8},{"id":257,"created_at":"2024-05-01T11:32:35.000000Z","updated_at":"2024-05-01T11:32:35.000000Z","user_id":2,"game_id":120,"total":10,"achieved":10},{"id":258,"created_at":"2024-05-01T11:32:35.000000Z","updated_at":"2024-05-01T11:32:35.000000Z","user_id":2,"game_id":121,"total":9,"achieved":9},{"id":259,"created_at":"2024-05-01T11:32:36.000000Z","updated_at":"2024-05-01T11:32:36.000000Z","user_id":2,"game_id":122,"total":11,"achieved":11},{"id":260,"created_at":"2024-05-01T11:32:36.000000Z","updated_at":"2024-05-01T11:32:36.000000Z","user_id":2,"game_id":123,"total":5,"achieved":5},{"id":261,"created_at":"2024-05-01T11:32:36.000000Z","updated_at":"2024-05-01T11:32:36.000000Z","user_id":2,"game_id":124,"total":10,"achieved":0},{"id":262,"created_at":"2024-05-01T11:32:36.000000Z","updated_at":"2024-05-01T11:32:36.000000Z","user_id":2,"game_id":125,"total":24,"achieved":24},{"id":263,"created_at":"2024-05-01T11:32:37.000000Z","updated_at":"2024-05-01T11:32:37.000000Z","user_id":2,"game_id":126,"total":24,"achieved":24},{"id":264,"created_at":"2024-05-01T11:32:37.000000Z","updated_at":"2024-05-01T11:32:37.000000Z","user_id":2,"game_id":127,"total":12,"achieved":12},{"id":265,"created_at":"2024-05-01T11:32:37.000000Z","updated_at":"2024-05-01T11:32:37.000000Z","user_id":2,"game_id":128,"total":20,"achieved":20},{"id":266,"created_at":"2024-05-01T11:32:37.000000Z","updated_at":"2024-05-01T11:32:37.000000Z","user_id":2,"game_id":129,"total":18,"achieved":18},{"id":267,"created_at":"2024-05-01T11:32:37.000000Z","updated_at":"2024-05-01T11:32:37.000000Z","user_id":2,"game_id":130,"total":39,"achieved":39},{"id":268,"created_at":"2024-05-01T11:32:38.000000Z","updated_at":"2024-05-01T11:32:38.000000Z","user_id":2,"game_id":131,"total":61,"achieved":43},{"id":269,"created_at":"2024-05-01T11:32:38.000000Z","updated_at":"2024-05-01T11:32:38.000000Z","user_id":2,"game_id":132,"total":3,"achieved":3},{"id":270,"created_at":"2024-05-01T11:32:38.000000Z","updated_at":"2024-05-01T11:32:38.000000Z","user_id":2,"game_id":133,"total":14,"achieved":0},{"id":271,"created_at":"2024-05-01T11:32:38.000000Z","updated_at":"2024-05-01T11:32:38.000000Z","user_id":2,"game_id":134,"total":29,"achieved":29},{"id":272,"created_at":"2024-05-01T11:32:38.000000Z","updated_at":"2024-05-01T11:32:38.000000Z","user_id":2,"game_id":135,"total":7,"achieved":7},{"id":273,"created_at":"2024-05-01T11:32:39.000000Z","updated_at":"2024-05-01T11:32:39.000000Z","user_id":2,"game_id":136,"total":83,"achieved":83},{"id":274,"created_at":"2024-05-01T11:32:39.000000Z","updated_at":"2024-05-01T11:32:39.000000Z","user_id":2,"game_id":137,"total":520,"achieved":274}]}]}